misst/__init__.py
misst/api.py
misst/predictor/predictor.py
misst/trainer/gui.py
misst/trainer/model_trainer.py
misst/trainer/preprocessor.py
misst/trainer/utils/datasets.py
misst/trainer/utils/error_handler.py
misst/trainer/utils/req_params.py
misst/trainer/utils/trainers.py
misst-0.1.1.dist-info/LICENSE
misst-0.1.1.dist-info/METADATA
misst-0.1.1.dist-info/WHEEL
misst-0.1.1.dist-info/top_level.txt
misst-0.1.1.dist-info/RECORD
