Metadata-Version: 2.1
Name: misst
Version: 0.1.1
Summary: Automated murine polysomnogram sleep staging for Python.
Author-email: Hudson Liu <hudsonliu0@gmail.com>
License: MIT License
Project-URL: Repository, https://github.com/Johns-Hopkins-CISRE/MISST
Keywords: misst,sleep staging,murine,polysomnogram,machine learning
Classifier: Development Status :: 3 - Alpha
Classifier: Intended Audience :: Science/Research
Classifier: Programming Language :: Python :: 3
Classifier: Operating System :: OS Independent
Classifier: License :: OSI Approved :: MIT License
Requires-Python: >=3.10
License-File: LICENSE
Requires-Dist: keras (>=2.9.0)
Requires-Dist: keras-tuner (>=1.1.3)
Requires-Dist: matplotlib (>=3.6.2)
Requires-Dist: mne (>=1.3.0)
Requires-Dist: numpy (>=1.22.3)
Requires-Dist: overrides (>=7.3.1)
Requires-Dist: pandas (>=1.5.2)
Requires-Dist: pyyaml (>=6.0.1)
Requires-Dist: scikit-learn (>=1.3.0)
Requires-Dist: tensorflow (>=2.9.1)
Requires-Dist: tensorflow-addons (>=0.20.0)
Requires-Dist: tqdm (>=4.64.1)
Provides-Extra: dev
Requires-Dist: twine (>=4.0.2) ; extra == 'dev'
